lambda_freezer/__init__.py
lambda_freezer-0.0.9.dist-info/LICENSE
lambda_freezer-0.0.9.dist-info/METADATA
lambda_freezer-0.0.9.dist-info/WHEEL
lambda_freezer-0.0.9.dist-info/top_level.txt
lambda_freezer-0.0.9.dist-info/RECORD
