Metadata-Version: 2.1
Name: lambda-freezer
Version: 0.0.9
Summary: Helpers to deploy lambda functions in an immutable way
Home-page: https://github.com/klagrange/lambda-freezer
Author: Keith Lagrange
Author-email: punolagrange@gmail.com
License: UNKNOWN
Platform: UNKNOWN
Classifier: Programming Language :: Python :: 3
Classifier: License :: OSI Approved :: MIT License
Classifier: Operating System :: OS Independent
Requires-Python: >=3.8
Requires-Dist: boto3
